CHANGELOG.rst
LICENSE
MANIFEST.in
README.rst
setup.py
docs/Makefile
docs/make.bat
docs/source/api.rst
docs/source/changelog.rst
docs/source/conf.py
docs/source/configuration.rst
docs/source/development.rst
docs/source/index.rst
docs/source/installation.rst
examples/slugs.conf
examples/user_group_mapping.csv
slugs/__init__.py
slugs/__init__.pyc
slugs/app.py
slugs/app.pyc
slugs/controllers.py
slugs/controllers.pyc
slugs/plugins.py
slugs/plugins.pyc
slugs/version.py
slugs/version.pyc
slugs.egg-info/PKG-INFO
slugs.egg-info/SOURCES.txt
slugs.egg-info/dependency_links.txt
slugs.egg-info/entry_points.txt
slugs.egg-info/requires.txt
slugs.egg-info/top_level.txt
slugs/__pycache__/__init__.cpython-34.pyc
slugs/__pycache__/__init__.cpython-35.pyc
slugs/__pycache__/__init__.cpython-36.pyc
slugs/__pycache__/__init__.cpython-37.pyc
slugs/__pycache__/app.cpython-34.pyc
slugs/__pycache__/app.cpython-35.pyc
slugs/__pycache__/app.cpython-36.pyc
slugs/__pycache__/app.cpython-37.pyc
slugs/__pycache__/controllers.cpython-34.pyc
slugs/__pycache__/controllers.cpython-35.pyc
slugs/__pycache__/controllers.cpython-36.pyc
slugs/__pycache__/controllers.cpython-37.pyc
slugs/__pycache__/plugins.cpython-34.pyc
slugs/__pycache__/plugins.cpython-35.pyc
slugs/__pycache__/plugins.cpython-36.pyc
slugs/__pycache__/plugins.cpython-37.pyc
slugs/__pycache__/version.cpython-34.pyc
slugs/__pycache__/version.cpython-35.pyc
slugs/__pycache__/version.cpython-36.pyc
slugs/__pycache__/version.cpython-37.pyc
slugs/tests/__init__.py
slugs/tests/__init__.pyc
slugs/tests/__pycache__/__init__.cpython-34.pyc
slugs/tests/__pycache__/__init__.cpython-35.pyc
slugs/tests/__pycache__/__init__.cpython-36.pyc
slugs/tests/__pycache__/__init__.cpython-37.pyc
slugs/tests/integration/__init__.py
slugs/tests/integration/__init__.pyc
slugs/tests/integration/conftest.py
slugs/tests/integration/test_slugs.py
slugs/tests/integration/__pycache__/conftest.cpython-27-PYTEST.pyc
slugs/tests/integration/__pycache__/test_slugs.cpython-27-PYTEST.pyc
slugs/tests/unit/__init__.py
slugs/tests/unit/__init__.pyc
slugs/tests/unit/test_app.py
slugs/tests/unit/test_controllers.py
slugs/tests/unit/test_plugins.py
