Metadata-Version: 1.1
Name: slugs
Version: 1.1.0
Summary: A Simple, Lightweight User Group Service.
Home-page: https://github.com/OpenKMIP/SLUGS
Author: Peter Hamilton
Author-email: peter.allen.hamilton@gmail.com
License: Apache License, Version 2.0
Keywords: authentication
Platform: UNKNOWN
Classifier: Environment :: Web Environment
Classifier: Framework :: CherryPy
Classifier: Intended Audience :: Developers
Classifier: License :: OSI Approved :: Apache Software License
Classifier: Natural Language :: English
Classifier: Operating System :: POSIX :: Linux
Classifier: Programming Language :: Python
Classifier: Programming Language :: Python :: 2
Classifier: Programming Language :: Python :: 2.7
Classifier: Programming Language :: Python :: 3
Classifier: Programming Language :: Python :: 3.4
Classifier: Programming Language :: Python :: 3.5
Classifier: Programming Language :: Python :: 3.6
Classifier: Programming Language :: Python :: 3.7
